nst_vgg19.py
nst_vgg19-0.3.1.dist-info/licenses/LICENSE
nst_vgg19-0.3.1.dist-info/METADATA
nst_vgg19-0.3.1.dist-info/WHEEL
nst_vgg19-0.3.1.dist-info/entry_points.txt
nst_vgg19-0.3.1.dist-info/top_level.txt
nst_vgg19-0.3.1.dist-info/RECORD
