Metadata-Version: 2.4
Name: nst_vgg19
Version: 0.3.1
Summary: Neural Style Transfer using VGG19
Home-page: https://github.com/alexanderbrodko/nst_vgg19
Author: Alexander Brodko
Author-email: xjesus666@yandex.ru
Classifier: Programming Language :: Python :: 3
Classifier: License :: OSI Approved :: MIT License
Classifier: Operating System :: OS Independent
Requires-Python: >=3.8
License-File: LICENSE
Requires-Dist: numpy
Requires-Dist: torch>=1.13
Requires-Dist: torchvision>=0.14
Requires-Dist: opencv-python
Requires-Dist: argparse
Dynamic: author
Dynamic: author-email
Dynamic: classifier
Dynamic: description
Dynamic: description-content-type
Dynamic: home-page
Dynamic: license-file
Dynamic: requires-dist
Dynamic: requires-python
Dynamic: summary
